classifier/__init__.py
classifier/_version.py
classifier/classifier.py
venv/bin/activate_this.py
classifier_reborn-3.0.4.dist-info/METADATA
classifier_reborn-3.0.4.dist-info/WHEEL
classifier_reborn-3.0.4.dist-info/entry_points.txt
classifier_reborn-3.0.4.dist-info/top_level.txt
classifier_reborn-3.0.4.dist-info/RECORD
