Metadata-Version: 2.1
Name: classifier-reborn
Version: 3.0.4
Summary: Classify the files in your Downloads folder into suitable destinations
Home-page: https://github.com/iwishiwasaneagle/classifier/
Author: Bhrigu Srivastava
Author-email: captain.bhrigu@gmail.com
Maintainer: Jan-Hendrik Ewers
Maintainer-email: dev.jh.ewers@gmail.com
License: MIT
Project-URL: Tracker, https://github.com/iwishiwasaneagle/classifier/issues
Platform: UNKNOWN
Classifier: Development Status :: 5 - Production/Stable
Classifier: License :: OSI Approved :: MIT License
Classifier: Operating System :: OS Independent
Requires-Dist: loguru (==0.6.0)
Requires-Dist: arrow (==1.2.2)
Requires-Dist: importlib-metadata ; python_version < "3.8"
Provides-Extra: test
Requires-Dist: setuptools ; extra == 'test'
Requires-Dist: pytest ; extra == 'test'
Requires-Dist: pytest-cov ; extra == 'test'
Requires-Dist: tox ; extra == 'test'
